fgch/__init__.py
fgch/commit_generator.py
gh_commit_history-0.1.3.dist-info/LICENSE
gh_commit_history-0.1.3.dist-info/METADATA
gh_commit_history-0.1.3.dist-info/WHEEL
gh_commit_history-0.1.3.dist-info/top_level.txt
gh_commit_history-0.1.3.dist-info/RECORD
