Metadata-Version: 2.1
Name: gh-commit-history
Version: 0.1.3
Summary: A small example package
Home-page: https://github.com/Vish-04/fake-github-commit-history
Author: Vish-04
Author-email: vakkati@ucdavis.edu
Project-URL: Bug Tracker, https://github.com/Vish-04/fake-github-commit-history/issues
Classifier: Programming Language :: Python :: 3
Classifier: License :: OSI Approved :: MIT License
Classifier: Operating System :: OS Independent
Requires-Python: >=3.6
License-File: LICENSE
